tfl_bus_monitor/__init__.py
tfl_bus_monitor/get_config_path.py
tfl_bus_monitor/tfl_bus_monitor.py
tfl_bus_monitor/config/busstop_config.ini
tfl_bus_monitor-0.11.dist-info/licenses/LICENSE
tfl_bus_monitor-0.11.dist-info/METADATA
tfl_bus_monitor-0.11.dist-info/WHEEL
tfl_bus_monitor-0.11.dist-info/entry_points.txt
tfl_bus_monitor-0.11.dist-info/top_level.txt
tfl_bus_monitor-0.11.dist-info/RECORD
