Metadata-Version: 2.4
Name: tfl_bus_monitor
Version: 0.11
Summary: TFL Bus Monitor - download Transport for London bus and tube arrival times
Author-email: David Klein <david@soinkleined.com>
License: MIT
Project-URL: Homepage, https://www.soinkleined.com
Keywords: tfl,bus,monitor,transport,london
Requires-Python: >=3.9
License-File: LICENSE
Requires-Dist: requests>=2.32.3
Requires-Dist: pytz>=2025.2
Dynamic: license-file
